mealpy/__init__.py
mealpy/multitask.py
mealpy/optimizer.py
mealpy/tuner.py
mealpy/bio_based/BBO.py
mealpy/bio_based/BBOA.py
mealpy/bio_based/BMO.py
mealpy/bio_based/EOA.py
mealpy/bio_based/IWO.py
mealpy/bio_based/SBO.py
mealpy/bio_based/SMA.py
mealpy/bio_based/SOA.py
mealpy/bio_based/SOS.py
mealpy/bio_based/TPO.py
mealpy/bio_based/TSA.py
mealpy/bio_based/VCS.py
mealpy/bio_based/WHO.py
mealpy/bio_based/__init__.py
mealpy/evolutionary_based/CRO.py
mealpy/evolutionary_based/DE.py
mealpy/evolutionary_based/EP.py
mealpy/evolutionary_based/ES.py
mealpy/evolutionary_based/FPA.py
mealpy/evolutionary_based/GA.py
mealpy/evolutionary_based/MA.py
mealpy/evolutionary_based/SHADE.py
mealpy/evolutionary_based/__init__.py
mealpy/human_based/BRO.py
mealpy/human_based/BSO.py
mealpy/human_based/CA.py
mealpy/human_based/CHIO.py
mealpy/human_based/FBIO.py
mealpy/human_based/GSKA.py
mealpy/human_based/HBO.py
mealpy/human_based/HCO.py
mealpy/human_based/ICA.py
mealpy/human_based/LCO.py
mealpy/human_based/QSA.py
mealpy/human_based/SARO.py
mealpy/human_based/SPBO.py
mealpy/human_based/SSDO.py
mealpy/human_based/TLO.py
mealpy/human_based/TOA.py
mealpy/human_based/WarSO.py
mealpy/human_based/__init__.py
mealpy/math_based/AOA.py
mealpy/math_based/CEM.py
mealpy/math_based/CGO.py
mealpy/math_based/CircleSA.py
mealpy/math_based/GBO.py
mealpy/math_based/HC.py
mealpy/math_based/INFO.py
mealpy/math_based/PSS.py
mealpy/math_based/RUN.py
mealpy/math_based/SCA.py
mealpy/math_based/SHIO.py
mealpy/math_based/TS.py
mealpy/math_based/__init__.py
mealpy/music_based/HS.py
mealpy/music_based/__init__.py
mealpy/physics_based/ASO.py
mealpy/physics_based/ArchOA.py
mealpy/physics_based/CDO.py
mealpy/physics_based/EFO.py
mealpy/physics_based/EO.py
mealpy/physics_based/EVO.py
mealpy/physics_based/FLA.py
mealpy/physics_based/HGSO.py
mealpy/physics_based/MVO.py
mealpy/physics_based/NRO.py
mealpy/physics_based/RIME.py
mealpy/physics_based/SA.py
mealpy/physics_based/TWO.py
mealpy/physics_based/WDO.py
mealpy-3.0.1.dist-info/LICENSE
mealpy-3.0.1.dist-info/METADATA
mealpy-3.0.1.dist-info/WHEEL
mealpy-3.0.1.dist-info/top_level.txt
mealpy-3.0.1.dist-info/RECORD
