Metadata-Version: 2.1
Name: mealpy
Version: 3.0.1
Summary: MEALPY: An Open-source Library for Latest Meta-heuristic Algorithms in Python
Home-page: https://github.com/thieu1995/mealpy
Author: Thieu
Author-email: nguyenthieu2102@gmail.com
License: GPLv3
Project-URL: Documentation, https://mealpy.readthedocs.io/
Project-URL: Source Code, https://github.com/thieu1995/mealpy
Project-URL: Bug Tracker, https://github.com/thieu1995/mealpy/issues
Project-URL: Change Log, https://github.com/thieu1995/mealpy/blob/master/ChangeLog.md
Project-URL: Forum, https://t.me/+fRVCJGuGJg1mNDg1
Keywords: optimization,metaheuristics,MHA,mathematical optimization,nature-inspired algorithms,evolutionary computation,soft computing,population-based algorithms,Stochastic optimization,Global optimization,Convergence analysis,Search space exploration,Local search,Computational intelligence,Black-box optimization,Robust optimization,Hybrid algorithms,Benchmark functions,Metaheuristic design,Performance analysis,Exploration versus exploitation,Self-adaptation,Constrained optimization,Intelligent
Classifier: Development Status :: 5 - Production/Stable
Classifier: Intended Audience :: Developers
Classifier: Intended Audience :: Education
Classifier: Intended Audience :: Information Technology
Classifier: Intended Audience :: Science/Research
Classifier: License :: OSI Approved :: GNU General Public License v3 (GPLv3)
Classifier: Natural Language :: English
Classifier: Programming Language :: Python :: 3
Classifier: Programming Language :: Python :: 3.7
Classifier: Programming Language :: Python :: 3.8
Classifier: Programming Language :: Python :: 3.9
Classifier: Programming Language :: Python :: 3.10
Classifier: Programming Language :: Python :: 3.11
Classifier: Topic :: System :: Benchmark
Classifier: Topic :: Scientific/Engineering
Classifier: Topic :: Scientific/Engineering :: Mathematics
Classifier: Topic :: Scientific/Engineering :: Artificial Intelligence
Classifier: Topic :: Scientific/Engineering :: Information Analysis
Classifier: Topic :: Scientific/Engineering :: Visualization
Classifier: Topic :: Scientific/Engineering :: Bio-Informatics
Classifier: Topic :: Software Development :: Build Tools
Classifier: Topic :: Software Development :: Libraries
Classifier: Topic :: Software Development :: Libraries :: Python Modules
Classifier: Topic :: Utilities
Requires-Python: >=3.7
License-File: LICENSE
Requires-Dist: numpy >=1.17.5
Requires-Dist: matplotlib >=3.3.0
Requires-Dist: scipy >=1.7.1
Requires-Dist: pandas >=1.2.0
Requires-Dist: opfunu >=1.0.0
Provides-Extra: dev
Requires-Dist: pytest >=7.0 ; extra == 'dev'
Requires-Dist: twine >=4.0.1 ; extra == 'dev'
